pyecotaxa/__init__.py
pyecotaxa/_version.py
pyecotaxa/archive.py
pyecotaxa/remote.py
pyecotaxa-0.0.4.dist-info/LICENSE
pyecotaxa-0.0.4.dist-info/METADATA
pyecotaxa-0.0.4.dist-info/WHEEL
pyecotaxa-0.0.4.dist-info/top_level.txt
pyecotaxa-0.0.4.dist-info/RECORD
